lastfm/__init__.py
lastfm/cli.py
lastfm_to_sqlite-0.2.3.dist-info/LICENSE
lastfm_to_sqlite-0.2.3.dist-info/METADATA
lastfm_to_sqlite-0.2.3.dist-info/WHEEL
lastfm_to_sqlite-0.2.3.dist-info/entry_points.txt
lastfm_to_sqlite-0.2.3.dist-info/top_level.txt
lastfm_to_sqlite-0.2.3.dist-info/RECORD
