Metadata-Version: 2.1
Name: lastfm-to-sqlite
Version: 0.2.3
Summary: Scrape LAST.FM playlists to SQLite
Home-page: https://github.com/hp0404/lastfm-to-sqlite
License: Apache License, Version 2.0
Project-URL: Documentation, https://lastfm.readthedocs.io/en/latest/
Project-URL: Issues, https://github.com/hp0404/lastfm-to-sqlite/issues
Project-URL: Changelog, https://github.com/hp0404/lastfm-to-sqlite/releases
Platform: UNKNOWN
Requires-Python: >=3.6
Requires-Dist: requests
Requires-Dist: sqlite-utils
Provides-Extra: docs
Requires-Dist: sphinx ; extra == 'docs'
Requires-Dist: sphinx-rtd-theme ; extra == 'docs'
Provides-Extra: test
Requires-Dist: pytest ; extra == 'test'
